korp/__init__.py
korp/api7_help.json
korp/api_help.json
korp/korp.py
korp-1.0.3.dist-info/METADATA
korp-1.0.3.dist-info/WHEEL
korp-1.0.3.dist-info/top_level.txt
korp-1.0.3.dist-info/RECORD
