Metadata-Version: 2.1
Name: korp
Version: 1.0.3
Summary: Korp API library for Python
Home-page: https://mikakalevi.com/nlp/python-korp/
Author: Mika Hämäläinen, Dept. of  Modern Languages, University of Helsinki
Author-email: mika.hamalainen@helsinki.fi
License: Apache License, Version 2.0
Keywords: Korp API
Platform: UNKNOWN
Classifier: Development Status :: 5 - Production/Stable
Classifier: Intended Audience :: Developers
Classifier: Topic :: Text Processing :: Linguistic
Classifier: Programming Language :: Python :: 2
Classifier: Programming Language :: Python :: 3
Classifier: Programming Language :: Python :: 2.6
Classifier: Programming Language :: Python :: 2.7
Requires-Dist: requests
